wxauto/__init__.py
wxauto/exceptions.py
wxauto/languages.py
wxauto/logger.py
wxauto/param.py
wxauto/uiautomation.py
wxauto/wx.py
wxauto/msgs/__init__.py
wxauto/msgs/attr.py
wxauto/msgs/base.py
wxauto/msgs/friend.py
wxauto/msgs/msg.py
wxauto/msgs/self.py
wxauto/msgs/type.py
wxauto/ui/__init__.py
wxauto/ui/base.py
wxauto/ui/chatbox.py
wxauto/ui/component.py
wxauto/ui/main.py
wxauto/ui/navigationbox.py
wxauto/ui/sessionbox.py
wxauto/utils/__init__.py
wxauto/utils/tools.py
wxauto/utils/win32.py
wxauto-39.1.18.dist-info/licenses/LICENSE
wxauto文件下载/test.py
wxauto-39.1.18.dist-info/METADATA
wxauto-39.1.18.dist-info/WHEEL
wxauto-39.1.18.dist-info/top_level.txt
wxauto-39.1.18.dist-info/RECORD
