Metadata-Version: 2.4
Name: wxauto
Version: 39.1.18
Summary: wxauto 3.9 V2 version
Author-email: Cluic <tikic@qq.com>
Requires-Python: <=3.15,>=3.8
License-File: LICENSE
Requires-Dist: tenacity
Requires-Dist: pywin32
Requires-Dist: pyperclip
Requires-Dist: pillow
Requires-Dist: psutil
Requires-Dist: colorama
Requires-Dist: comtypes
Dynamic: license-file
